{
  "$ref": "#/definitions/Room",
  "definitions": {
    "Room": {
      "type": "object",
      "properties": {
        "id": {
          "type": "number"
        },
        "name": {
          "type": "string"
        },
        "description": {
          "type": "string"
        },
        "participants": {
          "type": "array",
          "items": {
            "type": "string"
          },
          "default": []
        },
        "createdAt": {
          "type": "string",
          "format": "date-time",
          "default": "2025-07-04T07:01:06.702Z"
        },
        "isActive": {
          "type": "boolean",
          "default": true
        }
      },
      "required": [
        "id",
        "name"
      ],
      "additionalProperties": false
    }
  },
  "$schema": "http://json-schema.org/draft-07/schema#"
}